LICENSE
MANIFEST.in
README.md
setup.cfg
setup.py
dblue_mlwatch/__init__.py
dblue_mlwatch/config.py
dblue_mlwatch/exceptions.py
dblue_mlwatch/logger.py
dblue_mlwatch/ml_watch.py
dblue_mlwatch/version.py
dblue_mlwatch.egg-info/PKG-INFO
dblue_mlwatch.egg-info/SOURCES.txt
dblue_mlwatch.egg-info/dependency_links.txt
dblue_mlwatch.egg-info/requires.txt
dblue_mlwatch.egg-info/top_level.txt
dblue_mlwatch/configs/logger.yaml
dblue_mlwatch/configs/version.txt
dblue_mlwatch/constants/__init__.py
dblue_mlwatch/constants/event_type.py
dblue_mlwatch/constants/types.py
dblue_mlwatch/core/__init__.py
dblue_mlwatch/core/func_thread.py
dblue_mlwatch/stores/__init__.py
dblue_mlwatch/stores/base.py
dblue_mlwatch/stores/rest.py
dblue_mlwatch/system/__init__.py
dblue_mlwatch/system/cpu.py
dblue_mlwatch/system/disk.py
dblue_mlwatch/system/gpu.py
dblue_mlwatch/system/info.py
dblue_mlwatch/system/memory.py
dblue_mlwatch/system/network.py
dblue_mlwatch/trackers/__init__.py
dblue_mlwatch/trackers/base.py
dblue_mlwatch/trackers/feedback.py
dblue_mlwatch/trackers/metrics.py
dblue_mlwatch/trackers/prediction.py
dblue_mlwatch/utils/__init__.py
dblue_mlwatch/utils/json.py
dblue_mlwatch/utils/unit.py
dblue_mlwatch/validation/__init__.py
dblue_mlwatch/validation/schema_validator.py
dblue_mlwatch/validation/schemas/__init__.py
dblue_mlwatch/validation/schemas/feedback.py
dblue_mlwatch/validation/schemas/prediction.py
requirements/requirements-base.txt
requirements/requirements-dev.txt
requirements/requirements.txt
tests/__init__.py