Metadata-Version: 2.1
Name: dblue-mlwatch
Version: 0.0.9
Summary: Dblue MLWatch SDK for real-time machine learning model monitoring
Home-page: https://github.com/dblueai/dblue-mlwatch-python-sdk
Author: Rajesh Hegde
Author-email: rh@dblue.ai
Maintainer: Rajesh Hegde
Maintainer-email: rh@dblue.ai
License: Apache2
Keywords: dblue,machine-learning,deep-learning,monitoring,mlwatch
Platform: any
Classifier: Development Status :: 3 - Alpha
Classifier: License :: OSI Approved :: Apache Software License
Classifier: Natural Language :: English
Classifier: Programming Language :: Python
Classifier: Operating System :: OS Independent
Classifier: Intended Audience :: Developers
Classifier: Intended Audience :: Science/Research
Classifier: Topic :: Scientific/Engineering :: Artificial Intelligence
Provides-Extra: system-metrics
